mutyper/__init__.py
mutyper/_version.py
mutyper/ancestor.py
mutyper/cli.py
mutyper-1.0.2.dist-info/LICENSE
mutyper-1.0.2.dist-info/METADATA
mutyper-1.0.2.dist-info/WHEEL
mutyper-1.0.2.dist-info/entry_points.txt
mutyper-1.0.2.dist-info/top_level.txt
mutyper-1.0.2.dist-info/RECORD
