Metadata-Version: 2.1
Name: mutyper
Version: 1.0.2
Summary: ancestral k-mer mutation types for SNP data
Home-page: https://github.com/harrispopgen/mutyper
Author: William DeWitt
Author-email: wsdewitt@gmail.com
Classifier: Programming Language :: Python :: 3
Classifier: License :: OSI Approved :: MIT License
Classifier: Operating System :: OS Independent
Requires-Python: >=3.8
License-File: LICENSE
Requires-Dist: cyvcf2 (>=0.30.15)
Requires-Dist: pyfaidx
Requires-Dist: biopython
Requires-Dist: pandas
Requires-Dist: pyliftover
